README.md
setup.py
info_bpr/__init__.py
info_bpr.egg-info/PKG-INFO
info_bpr.egg-info/SOURCES.txt
info_bpr.egg-info/dependency_links.txt
info_bpr.egg-info/requires.txt
info_bpr.egg-info/top_level.txt
info_bpr/losses/__init__.py
info_bpr/losses/tf_losses.py
info_bpr/losses/th_losses.py