Metadata-Version: 1.2
Name: info-bpr
Version: 0.0.2
Summary: InfoBPR: Simple Yet Powerful Ranking Loss
Home-page: https://github.com/CrawlScript/InfoBPR
Author: Jun Hu
Author-email: hujunxianligong@gmail.com
License: GNU General Public License v3.0 (See LICENSE)
Platform: UNKNOWN
Requires-Python: >3.5.0
